connexion_faker/__init__.py
connexion_faker/aiohttp.py
connexion_faker/base.py
connexion_faker/django.py
connexion_faker-0.3.0.dist-info/LICENSE
connexion_faker-0.3.0.dist-info/METADATA
connexion_faker-0.3.0.dist-info/WHEEL
connexion_faker-0.3.0.dist-info/RECORD
